{
  "RealEstateStack-staging": {
    "VpcId": "vpc-02eabf970790766ec",
    "ParameterPathPrefix": "/qshelter/staging/",
    "JwtRefreshSecretArn": "arn:aws:secretsmanager:us-east-1:898751738669:secret:qshelter/staging/jwt-refresh-secret-IZHlvt",
    "EmailSecretArn": "arn:aws:secretsmanager:us-east-1:898751738669:secret:qshelter/staging/email-ENEIro",
    "Stage": "staging",
    "JwtAccessSecretArn": "arn:aws:secretsmanager:us-east-1:898751738669:secret:qshelter/staging/jwt-access-secret-Fo3y0c",
    "OAuthSecretArn": "arn:aws:secretsmanager:us-east-1:898751738669:secret:qshelter/staging/oauth-WF9nWO",
    "PaystackSecretArn": "arn:aws:secretsmanager:us-east-1:898751738669:secret:qshelter/staging/paystack-34sQ0x",
    "SecretsPathPrefix": "qshelter/staging/"
  }
}
