{
  "RealEstateStack-staging": {
    "VpcId": "vpc-040493d6382e6809d",
    "ParameterPathPrefix": "/qshelter/staging/",
    "JwtRefreshSecretArn": "arn:aws:secretsmanager:us-east-1:898751738669:secret:qshelter/staging/jwt-refresh-secret-f25YWp",
    "EmailSecretArn": "arn:aws:secretsmanager:us-east-1:898751738669:secret:qshelter/staging/email-qvuHP9",
    "Stage": "staging",
    "JwtAccessSecretArn": "arn:aws:secretsmanager:us-east-1:898751738669:secret:qshelter/staging/jwt-access-secret-hNr9Kj",
    "OAuthSecretArn": "arn:aws:secretsmanager:us-east-1:898751738669:secret:qshelter/staging/oauth-jDHJrI",
    "PaystackSecretArn": "arn:aws:secretsmanager:us-east-1:898751738669:secret:qshelter/staging/paystack-uQtlDP",
    "SecretsPathPrefix": "qshelter/staging/"
  }
}
